{"name":"Barleydb","body":"### BarleyDB\r\n# Simple light mysql database access library\r\n\r\nMany times you want to use simple db functions to interact with your databse but when you start you have to program exceptions catchers, error handlers and more.. now you can include our BarleyDB library and forget it! You only have to query your database. Thats all!\r\n\r\n### Example\r\n\r\n```\r\nrequire_once ('barley.class.php');\r\n\r\nBarley::init('localhost', 'user', 'pass', 'db');\r\n\r\n// Only use if you want to debug your querys\r\nBarley::enableDebug();\r\n\r\n// Execute your query\r\n$result = Barley::query('SELECT * FROM `beers` WHERE barley = 200');\r\n\r\n// Execute your query escaping params\r\n$result = Barley::query('SELECT * FROM `beers` WHERE barley_name = \"{demo}\"');\r\n\r\n// If you want to see your debug info\r\n$debugInfo = Barley::debugInfo();\r\nBarley::debug($debugInfo);\r\n```\r\n","tagline":"Simple light mysql access database library","google":"","note":"Don't delete this file! It's used internally to help with page regeneration."}